byted_overpass_ecom_video_trend_core/__init__.py
byted_overpass_ecom_video_trend_core-0.0.1.dist-info/METADATA
byted_overpass_ecom_video_trend_core-0.0.1.dist-info/WHEEL
byted_overpass_ecom_video_trend_core-0.0.1.dist-info/top_level.txt
byted_overpass_ecom_video_trend_core-0.0.1.dist-info/RECORD
